{"url": "https://www.fiverr.com/bernard18/design-modern-minimalist-logo?context_referrer=search_gigs&source=drop_down_filters&ref_ctx_id=dde06e925bac2a8cf7ac258bfff91102&pckg_id=1&pos=1&filtered_duration=7&context_type=rating&funnel=dde06e925bac2a8cf7ac258bfff91102&ref=delivery_time%3A7%7Cseller_language%3Aen%7Cis_seller_online%3Atrue%7Cpro%3Aany%7Cfile_format%3Ajpg%2Cpng&seller_online=true&imp_id=2cdd2a5a-bd4f-48e7-9d02-c63414a10ed1", "type0": "Basic", "price0": "57.88", "desc0": "2 High Quality logo, JPG and PNG (Transparent) files.", "type1": "Standard", "price1": "115.74", "desc1": "3 concepts, High Quality, JPG, PNG (Transparent), VECTOR AI & EPS", "type2": "Premium", "price2": "173.62", "desc2": "3 Highly Professional, JPG, PNG, VECTOR AI, EPS, social media KIT, STATIONERY DESIGN.", "package_row0": "Logo transparency", "package_row1": "Logo transparency", "package_row2": "Logo transparency", "package_row3": "", "package_row4": "Vector file", "package_row5": "Vector file", "package_row6": "Printable file", "package_row7": "Printable file", "package_row8": "Printable file", "package_row9": "", "package_row10": "Source file", "package_row11": "Source file", "package_row12": "", "package_row13": "", "package_row14": "Stationery designs", "package_row15": "", "package_row16": "", "package_row17": "Social media kit", "package_row18": "", "package_row19": "", "package_row20": "", "package_time0": "2 days", "package_time1": "3 days", "package_time2": "3 days", "revisions": 5}