{"url": "https://www.fiverr.com/zara_qureshi/design-professional-business-logo-for-you?context_referrer=search_gigs&source=drop_down_filters&ref_ctx_id=c8631fb8aa4b5f059b7640ed96e744c6&pckg_id=1&pos=5&filtered_duration=7&context_type=rating&funnel=c8631fb8aa4b5f059b7640ed96e744c6&ref=delivery_time%3A7%7Cseller_language%3Aen%7Cis_seller_online%3Atrue%7Cpro%3Aany%7Cfile_format%3Ajpg%2Cpng&seller_online=true&imp_id=8536c799-8a17-45cb-82b8-fa38f0e28645", "type0": "Basic", "price0": "19.04", "full_price0": "63.35", "desc0": "2 logo design, high quality JPEG, PNG formats with 3D Mock up.", "type1": "Standard", "price1": "66.64", "full_price1": "221.71", "desc1": "3 unique logo designs, high quality JPEG, PNG formats with 3D Mock up and vector file.", "type2": "Premium", "price2": "114.24", "full_price2": "380.08", "desc2": "4 pro logo designs, High quality JPEG, PNG with 3d mock up, vector & source files + Media kit", "package_row0": "", "package_row1": "", "package_row2": "", "package_row3": "", "package_row4": "", "package_row5": "", "package_row6": "", "package_row7": "", "package_row8": "", "package_row9": "", "package_row10": "", "package_row11": "", "package_row12": "", "package_row13": "", "package_row14": "", "package_row15": "", "package_row16": "", "package_row17": "", "package_row18": "", "package_row19": "", "package_row20": "", "package_time0": "2 days\n1 day\n(+\u20ac9.52)", "package_time1": "2 days\n1 day\n(+\u20ac14.28)", "package_time2": "3 days\n1 day\n(+\u20ac23.80)", "revisions": "5"}